{
  "genre": "fps",
  "title": "FPS",
  "games": [
    {
      "slug": "gallery",
      "title": "Gallery",
      "path": "games/gallery/",
      "icon": "🎯",
      "color": "#e0556b",
      "dims": "3D",
      "tags": ["shoot", "combo", "timed", "three.js"],
      "license": "MIT",
      "credit": "Gamf original"
    },
    {
      "slug": "drone-hunt",
      "title": "Drone Hunt",
      "path": "games/drone-hunt/",
      "icon": "🛸",
      "dims": "3D",
      "tags": ["survival", "shoot", "waves", "three.js"],
      "license": "MIT",
      "credit": "Gamf"
    },
    {
      "slug": "wave-range",
      "title": "Wave Range",
      "path": "games/wave-range/",
      "icon": "🎯",
      "dims": "3D",
      "tags": ["look", "shoot", "timed"],
      "license": "MIT",
      "credit": "Gamf sample"
    },
    {
      "slug": "quickdraw",
      "title": "Quickdraw",
      "path": "games/quickdraw/",
      "icon": "🤠",
      "color": "#ffae3c",
      "dims": "3D",
      "tags": ["reflex", "shoot", "duel", "three.js"],
      "license": "MIT",
      "credit": "Gamf original"
    }
  ]
}
